priceloop_api/__init__.py
priceloop_api/client.py
priceloop_api/errors.py
priceloop_api/py.typed
priceloop_api/types.py
priceloop_api/api/__init__.py
priceloop_api/api/column_api/__init__.py
priceloop_api/api/column_api/add_data_column.py
priceloop_api/api/column_api/add_formula_column.py
priceloop_api/api/column_api/delete_column.py
priceloop_api/api/column_api/get_column_attributes.py
priceloop_api/api/column_api/update_column_attributes.py
priceloop_api/api/column_api/update_column_is_gui_locked.py
priceloop_api/api/column_api/update_column_position.py
priceloop_api/api/column_api/update_column_visibility.py
priceloop_api/api/export_api/__init__.py
priceloop_api/api/export_api/list_table_export.py
priceloop_api/api/external_function_api/__init__.py
priceloop_api/api/external_function_api/create_external_function.py
priceloop_api/api/external_function_api/delete_external_function.py
priceloop_api/api/external_function_api/get_external_functions.py
priceloop_api/api/external_function_api/update_external_function.py
priceloop_api/api/import_api/__init__.py
priceloop_api/api/import_api/create_csv_import_job.py
priceloop_api/api/import_api/get_table_upload_csv_url.py
priceloop_api/api/other/__init__.py
priceloop_api/api/other/hello.py
priceloop_api/api/other/hello_auth.py
priceloop_api/api/plugin_api/__init__.py
priceloop_api/api/plugin_api/create_plugin.py
priceloop_api/api/plugin_api/delete_plugin.py
priceloop_api/api/plugin_api/get_plugin.py
priceloop_api/api/plugin_api/get_plugin_live_status.py
priceloop_api/api/plugin_api/get_plugin_tokens.py
priceloop_api/api/plugin_api/list_enabled_workspaces.py
priceloop_api/api/plugin_api/patch_plugin_data.py
priceloop_api/api/plugin_api/patch_plugin_external_data.py
priceloop_api/api/plugin_api/post_new_plugin_notifications.py
priceloop_api/api/plugin_api/prepare_ape_tables.py
priceloop_api/api/plugin_api/set_plugin_data.py
priceloop_api/api/plugin_api/set_plugin_external_data.py
priceloop_api_dev1-0.127.0.dist-info/LICENSE
priceloop_api_dev1-0.127.0.dist-info/METADATA
priceloop_api_dev1-0.127.0.dist-info/WHEEL
priceloop_api_dev1-0.127.0.dist-info/top_level.txt
priceloop_api_dev1-0.127.0.dist-info/RECORD
